rdutils/__init__.py
rdutils/get_incrementer.py
rdutils/image_sequence_streamer.py
rdutils/rtsp_recorder.py
rdutils/tcp_listener.py
rdutils/video_streamer.py
rdutils/video_to_images.py
rdutils-0.13.dist-info/LICENCE
rdutils-0.13.dist-info/METADATA
rdutils-0.13.dist-info/WHEEL
rdutils-0.13.dist-info/top_level.txt
rdutils-0.13.dist-info/RECORD
