Metadata-Version: 2.1
Name: rdutils
Version: 0.13
Summary: A set of python helper utilities
Home-page: https://gitlab.com/robdupre/rdutils
Author: Rob Dupre
Author-email: robdupre@gmail.com
Classifier: Programming Language :: Python :: 3
Classifier: License :: OSI Approved :: MIT License
Classifier: Operating System :: OS Independent
License-File: LICENCE
